<?xml version="1.0" encoding="utf-8" ?><dwsync><file name="class.color.php" server="s176.coreserver.jp//public_html/kodokai.jp/imaho/" local="3613495634" remote="3609986640" Dst="-1" /><file name="class.core-rest-api-endpoints.php" server="s176.coreserver.jp//public_html/kodokai.jp/imaho/" local="3613495634" remote="3609986640" Dst="-1" /><file name="class.media-extractor.php" server="s176.coreserver.jp//public_html/kodokai.jp/imaho/" local="3613495637" remote="3609986640" Dst="-1" /><file name="class.media-summary.php" server="s176.coreserver.jp//public_html/kodokai.jp/imaho/" local="3613495639" remote="3609986640" Dst="-1" /><file name="class.media.php" server="s176.coreserver.jp//public_html/kodokai.jp/imaho/" local="3613495639" remote="3609986640" Dst="-1" /><file name="icalendar-reader.php" server="s176.coreserver.jp//public_html/kodokai.jp/imaho/" local="3613495650" remote="3609986640" Dst="-1" /><file name="tonesque.php" server="s176.coreserver.jp//public_html/kodokai.jp/imaho/" local="3613495662" remote="3609986640" Dst="-1" /><file name="class.color.php" server="s176.coreserver.jp//public_html/kodokai.jp/" local="3615417067" remote="3614944260" Dst="-1" /><file name="class.core-rest-api-endpoints.php" server="s176.coreserver.jp//public_html/kodokai.jp/" local="3615417067" remote="3614944260" Dst="-1" /><file name="class.media-extractor.php" server="s176.coreserver.jp//public_html/kodokai.jp/" local="3615417069" remote="3614944260" Dst="-1" /><file name="class.media-summary.php" server="s176.coreserver.jp//public_html/kodokai.jp/" local="3615417070" remote="3614944260" Dst="-1" /><file name="class.media.php" server="s176.coreserver.jp//public_html/kodokai.jp/" local="3615417070" remote="3614944260" Dst="-1" /><file name="icalendar-reader.php" server="s176.coreserver.jp//public_html/kodokai.jp/" local="3615417072" remote="3614944260" Dst="-1" /><file name="tonesque.php" server="s176.coreserver.jp//public_html/kodokai.jp/" local="3615417076" remote="3614944260" Dst="-1" /><file name="class.jetpack-iframe-embed.php" server="s176.coreserver.jp//public_html/kodokai.jp/imaho/" local="3613495636" remote="3609986640" Dst="-1" /><file name="class.jetpack-automatic-install-skin.php" server="s176.coreserver.jp//public_html/kodokai.jp/" local="3615417068" remote="3614944260" Dst="-1" /><file name="class.jetpack-iframe-embed.php" server="s176.coreserver.jp//public_html/kodokai.jp/" local="3615417068" remote="3614944260" Dst="-1" /><file name="class.jetpack-search-performance-logger.php" server="s176.coreserver.jp//public_html/kodokai.jp/" local="3615417069" remote="3614944260" Dst="-1" /><file name="functions.wp-notify.php" server="s176.coreserver.jp//public_html/kodokai.jp/" local="3615417072" remote="3614944260" Dst="-1" /><file name="plugins.php" server="s176.coreserver.jp//public_html/kodokai.jp/" local="3615417076" remote="3614944260" Dst="-1" /><file name="widgets.php" server="s176.coreserver.jp//public_html/kodokai.jp/" local="3615417079" remote="3614944260" Dst="-1" /><file name="class.jetpack-automatic-install-skin.php" server="s176.coreserver.jp//public_html/kodokai.jp/imaho/" local="3613495636" remote="3609986640" Dst="-1" /><file name="class.jetpack-search-performance-logger.php" server="s176.coreserver.jp//public_html/kodokai.jp/imaho/" local="3613495637" remote="3609986640" Dst="-1" /><file name="functions.wp-notify.php" server="s176.coreserver.jp//public_html/kodokai.jp/imaho/" local="3613495650" remote="3609986640" Dst="-1" /><file name="plugins.php" server="s176.coreserver.jp//public_html/kodokai.jp/imaho/" local="3613495660" remote="3609986640" Dst="-1" /><file name="widgets.php" server="s176.coreserver.jp//public_html/kodokai.jp/imaho/" local="3613495666" remote="3609986640" Dst="-1" /></dwsync>