<?xml version="1.0" encoding="utf-8" ?><dwsync><file name="akismet-ja.mo" server="s176.coreserver.jp//public_html/kodokai.jp/imaho/" local="3613494616" remote="3610201620" Dst="-1" /><file name="akismet-ja.po" server="s176.coreserver.jp//public_html/kodokai.jp/imaho/" local="3613494616" remote="3610201620" Dst="-1" /><file name="all-in-one-seo-pack-ja.mo" server="s176.coreserver.jp//public_html/kodokai.jp/imaho/" local="3613494616" remote="3608128620" Dst="-1" /><file name="all-in-one-seo-pack-ja.po" server="s176.coreserver.jp//public_html/kodokai.jp/imaho/" local="3613494616" remote="3608128620" Dst="-1" /><file name="contact-form-7-ja.mo" server="s176.coreserver.jp//public_html/kodokai.jp/imaho/" local="3613494616" remote="3609986640" Dst="-1" /><file name="contact-form-7-ja.po" server="s176.coreserver.jp//public_html/kodokai.jp/imaho/" local="3613494616" remote="3609986640" Dst="-1" /><file name="google-sitemap-generator-ja.mo" server="s176.coreserver.jp//public_html/kodokai.jp/imaho/" local="3613494618" remote="3570274800" Dst="-1" /><file name="google-sitemap-generator-ja.po" server="s176.coreserver.jp//public_html/kodokai.jp/imaho/" local="3613494618" remote="3570274800" Dst="-1" /><file name="jetpack-ja.mo" server="s176.coreserver.jp//public_html/kodokai.jp/imaho/" local="3613494619" remote="3610676760" Dst="-1" /><file name="jetpack-ja.po" server="s176.coreserver.jp//public_html/kodokai.jp/imaho/" local="3613494619" remote="3610676760" Dst="-1" /><file name="akismet-ja.mo" server="s176.coreserver.jp//public_html/kodokai.jp/" local="3615416667" remote="3614943900" Dst="-1" /><file name="akismet-ja.po" server="s176.coreserver.jp//public_html/kodokai.jp/" local="3615416667" remote="3614943900" Dst="-1" /><file name="all-in-one-seo-pack-ja.mo" server="s176.coreserver.jp//public_html/kodokai.jp/" local="3615425743" remote="3614944200" Dst="-1" /><file name="all-in-one-seo-pack-ja.po" server="s176.coreserver.jp//public_html/kodokai.jp/" local="3615425743" remote="3614944200" Dst="-1" /><file name="contact-form-7-ja.mo" server="s176.coreserver.jp//public_html/kodokai.jp/" local="3615416668" remote="3614944200" Dst="-1" /><file name="contact-form-7-ja.po" server="s176.coreserver.jp//public_html/kodokai.jp/" local="3615416668" remote="3614944200" Dst="-1" /><file name="google-sitemap-generator-ja.mo" server="s176.coreserver.jp//public_html/kodokai.jp/" local="3615416668" remote="3570274800" Dst="-1" /><file name="google-sitemap-generator-ja.po" server="s176.coreserver.jp//public_html/kodokai.jp/" local="3615416668" remote="3570274800" Dst="-1" /><file name="jetpack-ja.mo" server="s176.coreserver.jp//public_html/kodokai.jp/" local="3615416669" remote="3614944260" Dst="-1" /><file name="jetpack-ja.po" server="s176.coreserver.jp//public_html/kodokai.jp/" local="3615416669" remote="3614944260" Dst="-1" /><file name="google-analytics-for-wordpress-ja.mo" server="s176.coreserver.jp//public_html/kodokai.jp/" local="3615416668" remote="3598700400" Dst="-1" /><file name="google-analytics-for-wordpress-ja.po" server="s176.coreserver.jp//public_html/kodokai.jp/" local="3615416668" remote="3598700400" Dst="-1" /><file name="google-analytics-for-wordpress-ja.po" server="s176.coreserver.jp//public_html/kodokai.jp/imaho/" local="3613494618" remote="3598756380" Dst="-1" /><file name="hello-dolly-ja.mo" server="s176.coreserver.jp//public_html/kodokai.jp/imaho/" local="3613494618" remote="3610935720" Dst="-1" /><file name="hello-dolly-ja.po" server="s176.coreserver.jp//public_html/kodokai.jp/imaho/" local="3613494618" remote="3610935720" Dst="-1" /><file name="hello-dolly-ja.mo" server="s176.coreserver.jp//public_html/kodokai.jp/" local="3615416668" remote="3610935720" Dst="-1" /><file name="hello-dolly-ja.po" server="s176.coreserver.jp//public_html/kodokai.jp/" local="3615416669" remote="3610935720" Dst="-1" /></dwsync>